drf_orderwcast/OrderingWCastFilter.py
drf_orderwcast/__init__.py
drf_orderwcast-1.0.6.dist-info/licenses/LICENSE
drf_orderwcast-1.0.6.dist-info/METADATA
drf_orderwcast-1.0.6.dist-info/WHEEL
drf_orderwcast-1.0.6.dist-info/top_level.txt
drf_orderwcast-1.0.6.dist-info/RECORD
