Metadata-Version: 2.4
Name: drf-orderwcast
Version: 1.0.6
Summary: A Django REST Framework OrderingFilter like class that handles sort with casting
Home-page: https://github.com/keter2002/drf-orderwcast
Author: João Manica
Author-email: joaoedisonmanica@gmail.com
License: MIT
Classifier: Development Status :: 3 - Alpha
Classifier: Framework :: Django
Classifier: Intended Audience :: Developers
Classifier: License :: OSI Approved :: MIT License
Classifier: Programming Language :: Python :: 3
License-File: LICENSE
Requires-Dist: djangorestframework
Dynamic: author
Dynamic: author-email
Dynamic: classifier
Dynamic: description
Dynamic: description-content-type
Dynamic: home-page
Dynamic: license
Dynamic: license-file
Dynamic: requires-dist
Dynamic: summary
